example_package_zaw/__init__.py
example_package_zaw/__main__.py
example_package_zaw/example.py
example_package_zaw/indi_va_table_template.html
example_package_zaw/oknserver_graph_plot_config.json
example_package_zaw/simpler_plot_config.json
example_package_zaw/sum_va_table_template.html
example_package_zaw-0.0.2.dist-info/LICENSE
example_package_zaw-0.0.2.dist-info/METADATA
example_package_zaw-0.0.2.dist-info/WHEEL
example_package_zaw-0.0.2.dist-info/entry_points.txt
example_package_zaw-0.0.2.dist-info/top_level.txt
example_package_zaw-0.0.2.dist-info/RECORD
